pytrainer/__init__.py
pytrainer/text.py
pytrainer-1.0.0.dist-info/METADATA
pytrainer-1.0.0.dist-info/WHEEL
pytrainer-1.0.0.dist-info/licenses/LICENSE
pytrainer-1.0.0.dist-info/RECORD
