Metadata-Version: 2.4
Name: pytrainer
Version: 1.0.0
Summary: AI made easy. Based on pytorch.
Project-URL: Homepage, https://github.com/Anthony-Maxwell1/pytrainer
Project-URL: Issues, https://github.com/Anthony-Maxwell1/pytrainer/issues
Author-email: Anthony Maxwell <amaxwell4013@gmail.com>
License-File: LICENSE
Classifier: Development Status :: 5 - Production/Stable
Classifier: License :: OSI Approved :: GNU General Public License (GPL)
Classifier: Operating System :: OS Independent
Classifier: Programming Language :: Python :: 3
Requires-Python: <=3.12,>=3.9
Requires-Dist: numpy>=1.21
Requires-Dist: torch>=1.10
